pg_simple/__init__.py
pg_simple/pg_simple.py
pg_simple/pool.py
tests/__init__.py
tests/main.py
pg_simple-0.2.4.dist-info/LICENSE
pg_simple-0.2.4.dist-info/METADATA
pg_simple-0.2.4.dist-info/WHEEL
pg_simple-0.2.4.dist-info/top_level.txt
pg_simple-0.2.4.dist-info/RECORD
