Metadata-Version: 1.1
Name: pg-simple
Version: 0.2.4
Summary: A simple wrapper for Python psycopg2 with connection pooling
Home-page: https://github.com/masroore/pg_simple
Author: Masroor Ehsan Choudhury
Author-email: masroore@gmail.com
License: BSD
Keywords: psycopg2 postgresql sql database
Platform: UNKNOWN
Classifier: Topic :: Database
Classifier: Programming Language :: Python
Classifier: Programming Language :: Python :: 3
Classifier: Programming Language :: Python :: 3.6
Classifier: Programming Language :: Python :: 3.7
Classifier: Programming Language :: Python :: 3.8
Classifier: Programming Language :: Python :: 3.9
Classifier: License :: OSI Approved :: BSD License
Classifier: Operating System :: OS Independent
Classifier: Intended Audience :: Developers
Classifier: Development Status :: 3 - Alpha
